hp2papi/__init__.py
hp2papi/api.py
hp2papi/api_func.py
hp2papi/classes.py
hp2papi/gRpcServicer.py
hp2papi/logger.py
hp2papi/peer.py
hp2papi/peerCollection.py
hp2papi/processHandler.py
hp2papi/pb2/__init__.py
hp2papi/pb2/api_pb2.py
hp2papi/pb2/api_pb2_grpc.py
hp2papi/peer/.DS_Store
hp2papi/peer/hp2p.go.peer
hp2papi/peer/hp2p.go.peer.exe
hp2papi/peer/hp2p.go.peer.mac
hp2p_api-1.0.9.dist-info/LICENSE
hp2p_api-1.0.9.dist-info/METADATA
hp2p_api-1.0.9.dist-info/WHEEL
hp2p_api-1.0.9.dist-info/top_level.txt
hp2p_api-1.0.9.dist-info/RECORD
